ExpertOptionApiV2/__init__.py
ExpertOptionApiV2/indicators.py
ExpertOptionApiV2/stable_api.py
ExpertOptionApiV2/_exceptions/__init__.py
ExpertOptionApiV2/_exceptions/Buying/BuyExceptions.py
ExpertOptionApiV2/_exceptions/Buying/__init__.py
ExpertOptionApiV2/api/__init__.py
ExpertOptionApiV2/api/constants.py
ExpertOptionApiV2/api/global_values.py
ExpertOptionApiV2/api/backend/__init__.py
ExpertOptionApiV2/api/backend/client.py
ExpertOptionApiV2/api/backend/server.py
ExpertOptionApiV2/api/backend/ws/__init__.py
ExpertOptionApiV2/api/backend/ws/profile.py
ExpertOptionApiV2/api/backend/ws/channels/__init__.py
ExpertOptionApiV2/api/backend/ws/channels/base.py
ExpertOptionApiV2/api/backend/ws/channels/ping.py
ExpertOptionApiV2/api/prebuild/__init__.py
ExpertOptionApiV2/api/prebuild/bot/__init__.py
ExpertOptionApiV2/api/prebuild/bot/aligator.py
ExpertOptionApiV2/api/prebuild/bot/rsi.py
expertoptionapi_v2-1.0.0.dist-info/licenses/LICENSE
expertoptionapi_v2-1.0.0.dist-info/METADATA
expertoptionapi_v2-1.0.0.dist-info/WHEEL
expertoptionapi_v2-1.0.0.dist-info/top_level.txt
expertoptionapi_v2-1.0.0.dist-info/RECORD
