Metadata-Version: 2.4
Name: ExpertOptionAPI-V2
Version: 1.0.0
Summary: Expert Option API V2 is a API for the ExpertOption broker
Home-page: https://github.com/ChipaDevTeam/ExpertOptionAPI-V2
Author: Vigo Walker
Author-email: vigopaul05@gmail.com
Classifier: Programming Language :: Python :: 3
Classifier: License :: OSI Approved :: MIT License
Classifier: Operating System :: OS Independent
Requires-Python: >=3.7
License-File: LICENSE
Requires-Dist: pause==0.3
Requires-Dist: simplejson==3.20.1
Requires-Dist: websocket-client==1.8.0
Dynamic: author
Dynamic: author-email
Dynamic: classifier
Dynamic: description
Dynamic: description-content-type
Dynamic: home-page
Dynamic: license-file
Dynamic: requires-dist
Dynamic: requires-python
Dynamic: summary
